wp2md/__init__.py
wp2md/_nbdev.py
wp2md/wp2md.py
wp2md-0.0.15.dist-info/LICENSE
wp2md-0.0.15.dist-info/METADATA
wp2md-0.0.15.dist-info/WHEEL
wp2md-0.0.15.dist-info/entry_points.txt
wp2md-0.0.15.dist-info/top_level.txt
wp2md-0.0.15.dist-info/RECORD
