Metadata-Version: 2.1
Name: wp2md
Version: 0.0.15
Summary: Convert wordpress articles to markdown
Home-page: https://github.com/outerbounds/wp2md/tree/master/
Author: Hamel Husain
Author-email: hamel@outerbounds.co
License: Apache Software License 2.0
Keywords: wordpress markdown
Platform: UNKNOWN
Classifier: Development Status :: 3 - Alpha
Classifier: Intended Audience :: Developers
Classifier: Natural Language :: English
Classifier: Programming Language :: Python :: 3.6
Classifier: Programming Language :: Python :: 3.7
Classifier: Programming Language :: Python :: 3.8
Classifier: Programming Language :: Python :: 3.9
Classifier: Programming Language :: Python :: 3.10
Classifier: License :: OSI Approved :: Apache Software License
Requires-Python: >=3.6
License-File: LICENSE
Requires-Dist: pip
Requires-Dist: packaging
Requires-Dist: markdownify
Provides-Extra: dev
